.coveragerc
.gitignore
.travis.yml
AUTHORS.rst
CHANGELOG.rst
LICENSE.txt
Makefile
README.rst
requirements.txt
setup.cfg
setup.py
tox.ini
docs/Makefile
docs/authors.rst
docs/changelog.rst
docs/conf.py
docs/index.rst
docs/license.rst
docs-misc/2013_017_001_51271.pdf
docs-misc/defaultports.txt
docs-misc/protocol-numbers.xhtml
docs-misc/silk.all
docs-misc/spec-links
docs/_static/.gitignore
src/flowproc/__init__.py
src/flowproc/flowprocctl.py
src/flowproc/flowprocd.py
src/flowproc/fluent.py
src/flowproc/ipfix.py
src/flowproc/netflowV5_lab.py
src/flowproc/testreader.py
src/flowproc/util.py
src/flowproc/v9_parser.py
src/flowproc/v9_state.py
src/flowproc.egg-info/PKG-INFO
src/flowproc.egg-info/SOURCES.txt
src/flowproc.egg-info/dependency_links.txt
src/flowproc.egg-info/entry_points.txt
src/flowproc.egg-info/not-zip-safe
src/flowproc.egg-info/requires.txt
src/flowproc.egg-info/top_level.txt
tests/conftest.py
tests/inspiration_skeleton.py
tests/test_v9_parser.py
tests/travis_install.sh